{"minecraft:recipes/decorations/crafting_table":{"criteria":{"unlock_right_away":"2026-06-05 07:24:43 +0000"},"done":true},"minecraft:adventure/adventuring_time":{"criteria":{"minecraft:forest":"2026-06-17 02:39:03 +0000","minecraft:sparse_jungle":"2026-06-05 07:30:27 +0000","minecraft:windswept_hills":"2026-06-17 02:45:05 +0000","minecraft:savanna":"2026-06-17 02:56:59 +0000","minecraft:plains":"2026-06-05 07:25:23 +0000"},"done":false},"minecraft:adventure/root":{"criteria":{"killed_by_something":"2026-06-05 07:27:31 +0000"},"done":true},"minecraft:recipes/decorations/chest":{"criteria":{"has_lots_of_items":"2026-06-05 07:28:43 +0000"},"done":true},"minecraft:nether/netherite_armor":{"criteria":{"netherite_armor":"2026-06-05 07:28:43 +0000"},"done":true},"minecraft:end/elytra":{"criteria":{"elytra":"2026-06-05 07:28:43 +0000"},"done":true},"minecraft:husbandry/root":{"criteria":{"consumed_item":"2026-06-05 07:29:19 +0000"},"done":true},"minecraft:husbandry/balanced_diet":{"criteria":{"golden_apple":"2026-06-05 07:29:19 +0000"},"done":false},"minecraft:adventure/who_needs_rockets":{"criteria":{"who_needs_rockets":"2026-06-05 07:29:58 +0000"},"done":true},"minecraft:adventure/totem_of_undying":{"criteria":{"used_totem":"2026-06-05 07:34:14 +0000"},"done":true},"minecraft:story/shiny_gear":{"criteria":{"diamond_helmet":"2026-06-17 02:39:02 +0000"},"done":true},"minecraft:recipes/brewing/cauldron":{"criteria":{"has_water_bucket":"2026-06-17 04:02:42 +0000"},"done":true},"minecraft:recipes/combat/bow":{"criteria":{"has_string":"2026-06-17 04:04:04 +0000"},"done":true},"minecraft:recipes/tools/fishing_rod":{"criteria":{"has_string":"2026-06-17 04:04:04 +0000"},"done":true},"minecraft:recipes/redstone/tripwire_hook":{"criteria":{"has_string":"2026-06-17 04:04:04 +0000"},"done":true},"minecraft:recipes/decorations/candle":{"criteria":{"has_string":"2026-06-17 04:04:04 +0000"},"done":true},"minecraft:recipes/tools/lead":{"criteria":{"has_string":"2026-06-17 04:04:04 +0000"},"done":true},"minecraft:recipes/building_blocks/white_wool_from_string":{"criteria":{"has_string":"2026-06-17 04:04:04 +0000"},"done":true},"minecraft:recipes/combat/crossbow":{"criteria":{"has_string":"2026-06-17 04:04:04 +0000"},"done":true},"minecraft:recipes/decorations/loom":{"criteria":{"has_string":"2026-06-17 04:04:04 +0000"},"done":true},"minecraft:recipes/tools/bundle":{"criteria":{"has_string":"2026-06-17 04:04:04 +0000"},"done":true},"minecraft:recipes/transportation/cherry_boat":{"criteria":{"in_water":"2026-06-17 04:04:14 +0000"},"done":true},"minecraft:recipes/transportation/bamboo_raft":{"criteria":{"in_water":"2026-06-17 04:04:14 +0000"},"done":true},"minecraft:recipes/transportation/spruce_boat":{"criteria":{"in_water":"2026-06-17 04:04:14 +0000"},"done":true},"minecraft:recipes/transportation/birch_boat":{"criteria":{"in_water":"2026-06-17 04:04:14 +0000"},"done":true},"minecraft:recipes/transportation/oak_boat":{"criteria":{"in_water":"2026-06-17 04:04:14 +0000"},"done":true},"minecraft:recipes/transportation/mangrove_boat":{"criteria":{"in_water":"2026-06-17 04:04:14 +0000"},"done":true},"minecraft:recipes/transportation/acacia_boat":{"criteria":{"in_water":"2026-06-17 04:04:14 +0000"},"done":true},"minecraft:recipes/transportation/pale_oak_boat":{"criteria":{"in_water":"2026-06-17 04:04:14 +0000"},"done":true},"minecraft:recipes/transportation/jungle_boat":{"criteria":{"in_water":"2026-06-17 04:04:14 +0000"},"done":true},"minecraft:recipes/transportation/dark_oak_boat":{"criteria":{"in_water":"2026-06-17 04:04:14 +0000"},"done":true},"minecraft:recipes/misc/red_dye_from_poppy":{"criteria":{"has_poppy":"2026-06-19 00:58:43 +0000"},"done":true},"minecraft:recipes/food/suspicious_stew_from_poppy":{"criteria":{"has_poppy":"2026-06-19 00:58:43 +0000"},"done":true},"DataVersion":4671}