{
  "stats": {
    "minecraft:mined": {
      "minecraft:short_grass": 1
    },
    "minecraft:custom": {
      "minecraft:time_since_rest": 13773,
      "minecraft:leave_game": 56,
      "minecraft:damage_taken": 33522,
      "minecraft:damage_absorbed": 7168,
      "minecraft:time_since_death": 13751,
      "minecraft:aviate_one_cm": 1374980,
      "minecraft:damage_dealt_absorbed": 4456,
      "minecraft:total_world_time": 432643,
      "minecraft:swim_one_cm": 40569,
      "minecraft:crouch_one_cm": 30003,
      "minecraft:climb_one_cm": 16165,
      "minecraft:deaths": 26,
      "minecraft:player_kills": 15,
      "minecraft:damage_resisted": 274,
      "minecraft:damage_blocked_by_shield": 20530,
      "minecraft:walk_one_cm": 642709,
      "minecraft:walk_under_water_one_cm": 32888,
      "minecraft:play_time": 432643,
      "minecraft:damage_dealt": 21893,
      "minecraft:jump": 3434,
      "minecraft:drop": 7,
      "minecraft:sprint_one_cm": 462701,
      "minecraft:fall_one_cm": 1737414,
      "minecraft:fly_one_cm": 1461299,
      "minecraft:interact_with_anvil": 2,
      "minecraft:walk_on_water_one_cm": 24699,
      "minecraft:sneak_time": 23280
    },
    "minecraft:picked_up": {
      "minecraft:ender_pearl": 1,
      "minecraft:poppy": 1,
      "minecraft:totem_of_undying": 1,
      "minecraft:wither_rose": 1,
      "minecraft:wheat_seeds": 1,
      "minecraft:netherite_leggings": 3,
      "minecraft:netherite_chestplate": 3,
      "minecraft:netherite_helmet": 3,
      "minecraft:netherite_boots": 3
    },
    "minecraft:dropped": {
      "minecraft:netherite_spear": 1,
      "minecraft:netherite_boots": 1,
      "minecraft:netherite_helmet": 1,
      "minecraft:ender_pearl": 1,
      "minecraft:netherite_leggings": 1,
      "minecraft:netherite_chestplate": 2
    },
    "minecraft:used": {
      "minecraft:grass_block": 46,
      "minecraft:netherite_helmet": 1,
      "minecraft:shield": 42,
      "minecraft:netherite_sword": 39,
      "minecraft:diamond_sword": 115,
      "minecraft:netherite_axe": 6,
      "minecraft:red_stained_glass": 1,
      "minecraft:firework_rocket": 159,
      "minecraft:elytra": 566,
      "minecraft:anvil": 1,
      "minecraft:soul_lantern": 1,
      "minecraft:netherite_spear": 15,
      "minecraft:obsidian": 8,
      "minecraft:spruce_wood": 2,
      "minecraft:wind_charge": 2181,
      "minecraft:jungle_leaves": 3,
      "minecraft:mace": 416,
      "minecraft:golden_apple": 182,
      "minecraft:barrier": 162,
      "minecraft:splash_potion": 178,
      "minecraft:poppy": 2,
      "minecraft:netherite_chestplate": 561,
      "minecraft:totem_of_undying": 1,
      "minecraft:sandstone": 212,
      "minecraft:ender_pearl": 387
    },
    "minecraft:killed_by": {
      "minecraft:player": 7
    }
  },
  "DataVersion": 4671
}